{
  "meta": {
    "klient_id": "demo_sro",
    "nazev": "Zkusebni s.r.o.",
    "ico": "123456789",
    "obdobi": 2024,
    "mesice_obdobi": 5,
    "period_label": "1.1.2024–9.5.2024",
    "datum_od": "2024-01-01",
    "datum_do": "2024-05-09",
    "updated": "2026-05-14T10:57:07",
    "kategorie_uj": "mikro",
    "rozvaha_format": "plny",
    "vzz_format": "plny",
    "priloha_format": "plna",
    "cf_povinne": true,
    "zmeny_vk_povinne": true,
    "audit_povinny": false,
    "pocet_zamestnancu": 0,
    "zdroj": "prubezne_vstup.xlsx",
    "typ": "live",
    "upozorneni": "Vykaz ziveho vykaznictvi - sestaven automaticky. Zahrnuje odpisy a rezervy z predvahy. Dan z prijmu je vypoctena vzorcem (21 % ze zakladu VH/1000*1000) bez danovych uprav. Pro ucely danoveho priznani zpracujte s ucetnim."
  },
  "rozvaha": {
    "aktiva_celkem": 2989000,
    "stala_aktiva": 356000,
    "dnm": 0.0,
    "dhm": 356000,
    "dfm": 0,
    "obezna_aktiva": 2632000,
    "zasoby": 1250000,
    "pohledavky_kr": 213000,
    "kfm": 0,
    "penezni_prostredky": 1169000,
    "cr_aktiv": 1000,
    "pasiva_celkem": 2989000,
    "vlastni_kapital": 227000,
    "zk": 100000,
    "vh_min_let": 142000,
    "nz_min_let": 0,
    "ztrata_min_let": -29000,
    "jiný_vh_min": 171000,
    "vh_bezne_obdobi": -14000,
    "cizi_zdroje": 2762000,
    "rezervy": 0,
    "zavazky_dl": 0,
    "zavazky_kr": 2762000,
    "cr_pasiv": 0.0,
    "dnm_prava": 0.0,
    "dhm_pozemky_stavby": 0,
    "dhm_movite": 356000,
    "dhm_zalohy": 0.5,
    "zasoby_mat": 0,
    "zasoby_nv": 0,
    "zasoby_zbozi": 1250000,
    "pp_pokladna": 934000,
    "pp_ucty": 235000,
    "kapitalove_fondy": 0,
    "fondy_ze_zisku": 0,
    "vh_za_obdobi": -14000,
    "zav_dodavatele": 44000,
    "zav_mzdy": 8000,
    "zav_sp_zp": 0,
    "zav_stat_dan": 0,
    "zav_jine": 2709000,
    "zav_spolecnici": 0,
    "bilancni_rovnost": true,
    "bilancni_rozdil": 0.0
  },
  "vzz": {
    "trzby_sluzby": 510000,
    "trzby_zbozi": 395000,
    "trzby_celkem": 905000,
    "vyk_spotreba": 811000,
    "nak_zbozi": 245000,
    "spotreba_mat_energie": 33000,
    "sluzby": 533000,
    "osobni_naklady": 33000,
    "mzdy": 33000,
    "odpisy": 51000,
    "ost_prov_vyn": 0,
    "ost_prov_nak": 17000,
    "provozni_vh": -7000,
    "trzby_prodany_dm": 0,
    "trzby_prodany_mat": 0,
    "nak_prodany_dm": 0,
    "nak_prodany_mat": 0,
    "vyn_dfm_podily": 0,
    "vyn_dfm_ostatni": 0,
    "nak_prodane_podily": 0,
    "nak_jiny_dfm": 0,
    "vyn_uroky": 0,
    "nak_uroky": 0,
    "ost_fin_vyn": 0,
    "ost_fin_nak": 8000,
    "financni_vh": -8000,
    "vh_pred_zdanenim": -14000,
    "dan": 0.0,
    "dan_je_odhad": true,
    "vh_po_zdaneni": -14000,
    "cisty_obrat": 905000
  },
  "cashflow": {
    "cf_vh_pred_zdanenim": -14000,
    "cf_odpisy": 51000,
    "cf_nak_uroky": 0,
    "cf_vyn_uroky": 0,
    "cf_upravy_nepen": 51000,
    "cf_pred_zmenami_pk": 37000,
    "cf_zmena_pohledavky": 129000,
    "cf_zmena_zasoby": 0,
    "cf_zmena_zavazky": 55000,
    "cf_zmena_cr_pas": -65000,
    "cf_zmena_cr_akt": 0,
    "cf_zmeny_pk_celkem": 118000,
    "cf_pred_zdanenim": 155000,
    "cf_dan": -0.0,
    "cf_vyn_uroky_prijate": 0,
    "cf_nak_uroky_zaplacene": 0,
    "cf_provozni": 155000,
    "cf_nabyte_dhm_dnm": 0,
    "cf_prodej_dm": 0,
    "cf_nabyte_fin_inv": 0,
    "cf_investicni": 0.0,
    "cf_prijate_uvery": 0,
    "cf_splatky_uveru": 0,
    "cf_dividendy": 0,
    "cf_financni": 0.0,
    "pp_zacatek": 1013000,
    "cf_cista_zmena": 155000,
    "pp_konec_cf": 1169000,
    "pp_konec_rozvaha": 1169000,
    "cf_minule_dostupne": true,
    "cf_poznamka": "Provozni CF – nepřímá metoda. Zmeny PK vypočteny z rozdilu vs minule obdobi. Investicni a financni CF = 0 (nelze zjistit z predvahy – doplnte rucne)."
  },
  "analyza": {
    "roa": -0.48,
    "roe": -6.35,
    "ros": -1.59,
    "bezna_likvidita": 0.95,
    "pohotova_likvidita": 0.5,
    "okamzita_likvidita": 0.42,
    "celkova_zadluzenost": 92.4,
    "mira_zadluzenosti": 12.16,
    "urokove_kryti": null,
    "doba_splaceni_dluhu": 17.8,
    "kryti_dm_vk": 0.64,
    "obrat_aktiv": 0.3,
    "obrat_dm": 2.54,
    "doba_obratu_zas": 497.2,
    "doba_obratu_pohl": 84.9,
    "doba_obratu_zav": 1098.5,
    "in05": 0.641,
    "in05_pasmo": "cervene",
    "in05_x": {
      "X1": 1.0822,
      "X2": 9.0,
      "X3": -0.0023,
      "X4": 0.3028,
      "X5": 0.953
    },
    "altman_z": 0.641,
    "altman_pasmo": "cervene",
    "altman_x": {
      "X1": 1.0822,
      "X2": 9.0,
      "X3": -0.0023,
      "X4": 0.3028,
      "X5": 0.953
    }
  },
  "analyza_ext": {},
  "minule": {
    "rok": 2024,
    "mesice_obdobi": 5,
    "period_label": "1.1.2024–9.5.2024",
    "aktiva_netto": 2989000,
    "pasiva_celkem": 2989000,
    "stala_netto": 356000,
    "obezna_netto": 2632000,
    "zasoby": 1250000,
    "pohledavky_kr": 213000,
    "pp": 1169000,
    "vk": 227000,
    "zav_kr": 2762000,
    "cizi_zdroje": 2762000,
    "trzby_vyrobky_sluzby": 510000,
    "trzby_zbozi": 395000,
    "trzby_celkem": 905000,
    "vyk_spotreba": 811000,
    "osobni_naklady": 33000,
    "odpisy": 51000,
    "provozni_vh": -7000,
    "financni_vh": -8000,
    "vh_pred_zdanenim": -14000,
    "dan_z_prijmu": 0.0,
    "vh_za_obdobi": -14000,
    "cisty_obrat": 905000,
    "archivovano": "2026-05-14T10:57:07"
  }
}